mycalc/calculator.py
jinjin00123-0.0.1.dist-info/METADATA
jinjin00123-0.0.1.dist-info/WHEEL
jinjin00123-0.0.1.dist-info/top_level.txt
jinjin00123-0.0.1.dist-info/RECORD
