Metadata-Version: 2.1
Name: jinjin00123
Version: 0.0.1
Summary: oss-dev my calculator 0001
Home-page: https://github.com/DSLKD/calc0001
Download-URL: https://github.com/DSLKD/calc0001/archive/refs/tags/v0.0.1.zip
Author: min
License: UNKNOWN
Platform: UNKNOWN
Classifier: Programming Language :: Python :: 3
